nutrition_tracker_lib/__init__.py
nutrition_tracker_lib/tracker.py
nutrition_tracker_lib-0.1.0.dist-info/METADATA
nutrition_tracker_lib-0.1.0.dist-info/WHEEL
nutrition_tracker_lib-0.1.0.dist-info/top_level.txt
nutrition_tracker_lib-0.1.0.dist-info/RECORD
