Metadata-Version: 2.4
Name: nutrition-tracker-lib
Version: 0.1.0
Summary: A library for tracking nutrition data using the USDA API
Author: Your Name
Author-email: akhilareddykandadi@gmail.com
Classifier: Programming Language :: Python :: 3
Classifier: License :: OSI Approved :: MIT License
Classifier: Operating System :: OS Independent
Requires-Python: >=3.6
Requires-Dist: requests>=2.25.0
Requires-Dist: django>=3.0
Dynamic: author
Dynamic: author-email
Dynamic: classifier
Dynamic: description-content-type
Dynamic: requires-dist
Dynamic: requires-python
Dynamic: summary
